<?xml version='1.0' encoding='UTF-8'?>
<?artifactRepository version='1.1.0'?>
<repository name='Tracker Product Artifacts' type='org.eclipse.equinox.p2.artifact.repository.simpleRepository' version='1'>
  <properties size='1'>
    <property name='p2.timestamp' value='1352417683925'/>
  </properties>
  <mappings size='3'>
    <rule filter='(&amp; (classifier=osgi.bundle))' output='${repoUrl}/plugins/${id}_${version}.jar'/>
    <rule filter='(&amp; (classifier=binary))' output='${repoUrl}/binary/${id}_${version}'/>
    <rule filter='(&amp; (classifier=org.eclipse.update.feature))' output='${repoUrl}/features/${id}_${version}.jar'/>
  </mappings>
  <artifacts size='214'>
    <artifact classifier='osgi.bundle' id='org.eclipse.equinox.p2.ui.sdk.scheduler' version='1.1.0.v20110815-1744'>
      <properties size='3'>
        <property name='artifact.size' value='60467'/>
        <property name='download.size' value='60467'/>
        <property name='download.md5' value='616cc6e437c498e25df2f4a953901749'/>
      </properties>
    </artifact>
    <artifact classifier='binary' id='org.eclipse.equinox.executable_root.cocoa.macosx.ppc' version='3.6.0.v20120522-1813-7P7OG2BFLWUl7UmbVUO9iCm'>
      <properties size='1'>
        <property name='download.size' value='17117'/>
      </properties>
    </artifact>
    <artifact classifier='osgi.bundle' id='org.eclipse.equinox.app' version='1.3.100.v20120522-1841'>
      <properties size='3'>
        <property name='artifact.size' value='86391'/>
        <property name='download.size' value='86391'/>
        <property name='download.md5' value='19fb7656635e0177fb8ee1752e59b434'/>
      </properties>
    </artifact>
    <artifact classifier='osgi.bundle' id='org.eclipse.swt.win32.win32.x86' version='3.8.1.v3834e'>
      <properties size='3'>
        <property name='artifact.size' value='2701188'/>
        <property name='download.size' value='2701188'/>
        <property name='download.md5' value='0be2f9e71c8a2ac225b5b0f50f5995c6'/>
      </properties>
    </artifact>
    <artifact classifier='osgi.bundle' id='com.ibm.icu' version='4.4.2.v20110823'>
      <properties size='3'>
        <property name='artifact.size' value='6701200'/>
        <property name='download.size' value='6701200'/>
        <property name='download.md5' value='b0d01f0723b407b4018abeae78dcb068'/>
      </properties>
    </artifact>
    <artifact classifier='osgi.bundle' id='org.eclipse.update.scheduler' version='3.2.400.v20120530-120908'>
      <properties size='3'>
        <property name='artifact.size' value='33060'/>
        <property name='download.size' value='33060'/>
        <property name='download.md5' value='d52ef200e7bfc7dcd72f628cdbc05a9b'/>
      </properties>
    </artifact>
    <artifact classifier='osgi.bundle' id='org.eclipse.ui.forms' version='3.5.200.v20120521-2332'>
      <properties size='3'>
        <property name='artifact.size' value='302118'/>
        <property name='download.size' value='302118'/>
        <property name='download.md5' value='eab65088dc21d97f823469fd9eace171'/>
      </properties>
    </artifact>
    <artifact classifier='binary' id='org.eclipse.equinox.executable_root.carbon.macosx.x86' version='3.6.0.v20120522-1813-7P7OG2BFLWUl7UmbVUO9iCm'>
      <properties size='1'>
        <property name='download.size' value='18001'/>
      </properties>
    </artifact>
    <artifact classifier='osgi.bundle' id='org.eclipse.update.core.win32' version='3.2.300.v20120530-120908'>
      <properties size='3'>
        <property name='artifact.size' value='87556'/>
        <property name='download.size' value='87556'/>
        <property name='download.md5' value='d4d7546c128118f913334df99bb01b42'/>
      </properties>
    </artifact>
    <artifact classifier='osgi.bundle' id='org.eclipse.equinox.p2.updatesite' version='1.0.400.v20120412-1615'>
      <properties size='3'>
        <property name='artifact.size' value='83984'/>
        <property name='download.size' value='83984'/>
        <property name='download.md5' value='e2f49e605cc9615fa2e7ed3bd8ff91af'/>
      </properties>
    </artifact>
    <artifact classifier='osgi.bundle' id='org.eclipse.compare.core' version='3.5.200.v20120522-1148'>
      <properties size='3'>
        <property name='artifact.size' value='63243'/>
        <property name='download.size' value='63243'/>
        <property name='download.md5' value='f4602e6f77241a3ffccb33a9a347c17e'/>
      </properties>
    </artifact>
    <artifact classifier='binary' id='org.eclipse.equinox.executable_root.gtk.linux.x86_64' version='3.6.0.v20120522-1813-7P7OG2BFLWUl7UmbVUO9iCm'>
      <properties size='1'>
        <property name='download.size' value='179849'/>
      </properties>
    </artifact>
    <artifact classifier='osgi.bundle' id='org.eclipse.ecf.filetransfer' version='5.0.0.v20120610-1946'>
      <properties size='3'>
        <property name='artifact.size' value='51713'/>
        <property name='download.size' value='51713'/>
        <property name='download.md5' value='37d1b7ca055316be603f3e782a6a8de1'/>
      </properties>
    </artifact>
    <artifact classifier='osgi.bundle' id='javax.servlet' version='3.0.0.v201112011016'>
      <properties size='3'>
        <property name='artifact.size' value='201594'/>
        <property name='download.size' value='201594'/>
        <property name='download.md5' value='54ca9d204ab946d8e44d24ab2c66f2ef'/>
      </properties>
    </artifact>
    <artifact classifier='osgi.bundle' id='org.apache.felix.gogo.command' version='0.8.0.v201108120515'>
      <properties size='3'>
        <property name='artifact.size' value='57580'/>
        <property name='download.size' value='57580'/>
        <property name='download.md5' value='5683b3d4655fe69a91d92ec7d7da0f0d'/>
      </properties>
    </artifact>
    <artifact classifier='osgi.bundle' id='org.apache.commons.httpclient' version='3.1.0.v201012070820'>
      <properties size='3'>
        <property name='artifact.size' value='321633'/>
        <property name='download.size' value='321633'/>
        <property name='download.md5' value='169fea92000c62622dd87e567b6c04a7'/>
      </properties>
    </artifact>
    <artifact classifier='osgi.bundle' id='org.eclipse.jsch.ui' version='1.1.400.v20120522-1148'>
      <properties size='3'>
        <property name='artifact.size' value='90637'/>
        <property name='download.size' value='90637'/>
        <property name='download.md5' value='f3fb86086ad630a06fe02aeccd8e56c6'/>
      </properties>
    </artifact>
    <artifact classifier='osgi.bundle' id='org.eclipse.core.net.win32.x86' version='1.0.100.v20120522-1148'>
      <properties size='3'>
        <property name='artifact.size' value='30970'/>
        <property name='download.size' value='30970'/>
        <property name='download.md5' value='5df967d465667b46b6be6938259866ab'/>
      </properties>
    </artifact>
    <artifact classifier='binary' id='org.eclipse.equinox.executable_root.gtk.solaris.x86' version='3.6.0.v20120522-1813-7P7OG2BFLWUl7UmbVUO9iCm'>
      <properties size='1'>
        <property name='download.size' value='11044'/>
      </properties>
    </artifact>
    <artifact classifier='osgi.bundle' id='org.eclipse.ecf.identity' version='3.1.200.v20120610-1946'>
      <properties size='3'>
        <property name='artifact.size' value='54408'/>
        <property name='download.size' value='54408'/>
        <property name='download.md5' value='d9c3d5358e6fad8207d6990fccc9e817'/>
      </properties>
    </artifact>
    <artifact classifier='org.eclipse.update.feature' id='com.verticon.tracker.product.desktop' version='0.7.0.201211081713-16-312322192824'>
      <properties size='2'>
        <property name='download.contentType' value='application/zip'/>
        <property name='download.size' value='3948'/>
      </properties>
    </artifact>
    <artifact classifier='osgi.bundle' id='org.eclipse.debug.core' version='3.7.100.v20120521-2012'>
      <properties size='3'>
        <property name='artifact.size' value='346430'/>
        <property name='download.size' value='346430'/>
        <property name='download.md5' value='bf58cbc6a4f20953d1b1fff542bb294b'/>
      </properties>
    </artifact>
    <artifact classifier='osgi.bundle' id='org.eclipse.ui.editors' version='3.8.0.v20120523-1540'>
      <properties size='3'>
        <property name='artifact.size' value='573591'/>
        <property name='download.size' value='573591'/>
        <property name='download.md5' value='6f4c057fd50bb9954ed1c88b51620e2b'/>
      </properties>
    </artifact>
    <artifact classifier='osgi.bundle' id='org.eclipse.equinox.p2.repository.tools' version='2.0.100.v20120501-1314'>
      <properties size='3'>
        <property name='artifact.size' value='235501'/>
        <property name='download.size' value='235501'/>
        <property name='download.md5' value='d1da602cba3ef29cb6f1e6ad2f3fd3e0'/>
      </properties>
    </artifact>
    <artifact classifier='osgi.bundle' id='org.eclipse.core.jobs' version='3.5.200.v20120521-2346'>
      <properties size='3'>
        <property name='artifact.size' value='92324'/>
        <property name='download.size' value='92324'/>
        <property name='download.md5' value='232cc2153198de690f4ffc6b9cadabf8'/>
      </properties>
    </artifact>
    <artifact classifier='osgi.bundle' id='org.eclipse.debug.ui' version='3.8.1.v20120718-192144'>
      <properties size='3'>
        <property name='artifact.size' value='2612316'/>
        <property name='download.size' value='2612316'/>
        <property name='download.md5' value='b65c823b56878c63ff800c3993879970'/>
      </properties>
    </artifact>
    <artifact classifier='osgi.bundle' id='org.eclipse.equinox.p2.repository' version='2.2.0.v20120524-1945'>
      <properties size='3'>
        <property name='artifact.size' value='131859'/>
        <property name='download.size' value='131859'/>
        <property name='download.md5' value='426e76b03aee5e9bb263c02b9fa64ef5'/>
      </properties>
    </artifact>
    <artifact classifier='osgi.bundle' id='org.eclipse.core.net' version='1.2.200.v20120522-1148'>
      <properties size='3'>
        <property name='artifact.size' value='70466'/>
        <property name='download.size' value='70466'/>
        <property name='download.md5' value='834b4b45cacbe4554ed94c8c727f4011'/>
      </properties>
    </artifact>
    <artifact classifier='osgi.bundle' id='org.eclipse.core.filebuffers' version='3.5.200.v20120523-1310'>
      <properties size='3'>
        <property name='artifact.size' value='114685'/>
        <property name='download.size' value='114685'/>
        <property name='download.md5' value='1451b302bf8069bec719b721cbe97cea'/>
      </properties>
    </artifact>
    <artifact classifier='osgi.bundle' id='org.eclipse.jface' version='3.8.0.v20120521-2332'>
      <properties size='3'>
        <property name='artifact.size' value='1090097'/>
        <property name='download.size' value='1090097'/>
        <property name='download.md5' value='218e74de31b8ab9ba8b2a612b9722ac8'/>
      </properties>
    </artifact>
    <artifact classifier='osgi.bundle' id='org.sat4j.pb' version='2.3.0.v20110329'>
      <properties size='3'>
        <property name='artifact.size' value='140721'/>
        <property name='download.size' value='140721'/>
        <property name='download.md5' value='8690daa37259608b568d973b9933b2aa'/>
      </properties>
    </artifact>
    <artifact classifier='org.eclipse.update.feature' id='org.eclipse.equinox.p2.rcp.feature' version='1.1.0.v20120524-0542-785EoBqNKNYz-GX2sUgCaBty3dqr'>
      <properties size='3'>
        <property name='artifact.size' value='4096'/>
        <property name='download.size' value='30957'/>
        <property name='download.contentType' value='application/zip'/>
      </properties>
    </artifact>
    <artifact classifier='osgi.bundle' id='org.eclipse.team.core' version='3.6.100.v20120524-0627'>
      <properties size='3'>
        <property name='artifact.size' value='398409'/>
        <property name='download.size' value='398409'/>
        <property name='download.md5' value='f14d08622931fd5406d3537d9d31f6ba'/>
      </properties>
    </artifact>
    <artifact classifier='osgi.bundle' id='org.eclipse.ui.browser' version='3.4.1.v20120718-113058'>
      <properties size='3'>
        <property name='artifact.size' value='192654'/>
        <property name='download.size' value='192654'/>
        <property name='download.md5' value='a66859d893d6acb3cde93bfd0412579a'/>
      </properties>
    </artifact>
    <artifact classifier='osgi.bundle' id='org.eclipse.core.boot' version='3.1.300.v20120523-2004'>
      <properties size='3'>
        <property name='artifact.size' value='7498'/>
        <property name='download.size' value='7498'/>
        <property name='download.md5' value='fa9f0a8efa023c3b58672bd90a6373a5'/>
      </properties>
    </artifact>
    <artifact classifier='osgi.bundle' id='org.eclipse.equinox.http.jetty' version='3.0.0.v20120522-1841'>
      <properties size='3'>
        <property name='artifact.size' value='25259'/>
        <property name='download.size' value='25259'/>
        <property name='download.md5' value='816af68aa394136e92c0f625eb5eb7a4'/>
      </properties>
    </artifact>
    <artifact classifier='osgi.bundle' id='org.eclipse.osgi' version='3.8.1.v20120830-144521'>
      <properties size='3'>
        <property name='artifact.size' value='1396459'/>
        <property name='download.size' value='1396459'/>
        <property name='download.md5' value='0c13c5a93ef25b462716ef98f370ce94'/>
      </properties>
    </artifact>
    <artifact classifier='osgi.bundle' id='org.eclipse.equinox.io' version='1.0.400.v20120522-2049'>
      <properties size='3'>
        <property name='artifact.size' value='41129'/>
        <property name='download.size' value='41129'/>
        <property name='download.md5' value='b05546e92db5e54612cad40210ef5176'/>
      </properties>
    </artifact>
    <artifact classifier='osgi.bundle' id='org.eclipse.equinox.p2.touchpoint.natives' version='1.1.0.v20120524-0542'>
      <properties size='3'>
        <property name='artifact.size' value='52954'/>
        <property name='download.size' value='52954'/>
        <property name='download.md5' value='02218856447b6b3fb420375f7f03d50d'/>
      </properties>
    </artifact>
    <artifact classifier='osgi.bundle' id='org.eclipse.ant.core' version='3.2.400.v20120523-1742'>
      <properties size='3'>
        <property name='artifact.size' value='99107'/>
        <property name='download.size' value='99107'/>
        <property name='download.md5' value='a6e17312dc0d2100d0fd752f04d8ee44'/>
      </properties>
    </artifact>
    <artifact classifier='osgi.bundle' id='org.eclipse.equinox.wireadmin' version='1.0.400.v20120522-2049'>
      <properties size='3'>
        <property name='artifact.size' value='38414'/>
        <property name='download.size' value='38414'/>
        <property name='download.md5' value='f3fa068291b6ce480232354fd4ccb77a'/>
      </properties>
    </artifact>
    <artifact classifier='osgi.bundle' id='org.eclipse.compare.win32' version='1.0.200.v20120522-1148'>
      <properties size='3'>
        <property name='artifact.size' value='39104'/>
        <property name='download.size' value='39104'/>
        <property name='download.md5' value='84ea0af06e53803c1ecfdbba1aa46682'/>
      </properties>
    </artifact>
    <artifact classifier='osgi.bundle' id='org.eclipse.swt' version='3.8.1.v3834e'>
      <properties size='3'>
        <property name='artifact.size' value='18537'/>
        <property name='download.size' value='18537'/>
        <property name='download.md5' value='4caaa4448e53d3869965476db0d49e37'/>
      </properties>
    </artifact>
    <artifact classifier='osgi.bundle' id='org.apache.lucene' version='2.9.1.v201101211721'>
      <properties size='3'>
        <property name='artifact.size' value='71018'/>
        <property name='download.size' value='71018'/>
        <property name='download.md5' value='b4dd9c45515c5ad8ecfa69e358a78c81'/>
      </properties>
    </artifact>
    <artifact classifier='binary' id='org.eclipse.equinox.executable_root.gtk.solaris.sparc' version='3.6.0.v20120522-1813-7P7OG2BFLWUl7UmbVUO9iCm'>
      <properties size='1'>
        <property name='download.size' value='12421'/>
      </properties>
    </artifact>
    <artifact classifier='osgi.bundle' id='org.eclipse.equinox.p2.core' version='2.2.0.v20120430-0525'>
      <properties size='3'>
        <property name='artifact.size' value='72598'/>
        <property name='download.size' value='72598'/>
        <property name='download.md5' value='e66fb33144ba1da466711e47440d1344'/>
      </properties>
    </artifact>
    <artifact classifier='osgi.bundle' id='org.eclipse.platform' version='3.8.1.v201209141540'>
      <properties size='2'>
        <property name='artifact.size' value='4096'/>
        <property name='download.size' value='399181'/>
      </properties>
    </artifact>
    <artifact classifier='osgi.bundle' id='org.eclipse.equinox.simpleconfigurator.manipulator' version='2.0.0.v20110808-1657'>
      <properties size='3'>
        <property name='artifact.size' value='24055'/>
        <property name='download.size' value='24055'/>
        <property name='download.md5' value='a2419cd092a5485477aead0082a8263e'/>
      </properties>
    </artifact>
    <artifact classifier='osgi.bundle' id='org.eclipse.ui.workbench' version='3.8.1.v20120816-082703'>
      <properties size='3'>
        <property name='artifact.size' value='4173196'/>
        <property name='download.size' value='4173196'/>
        <property name='download.md5' value='61cfc3627533734c5b2f3f9ae01832a7'/>
      </properties>
    </artifact>
    <artifact classifier='osgi.bundle' id='org.eclipse.equinox.metatype' version='1.2.0.v20120522-1841'>
      <properties size='3'>
        <property name='artifact.size' value='78964'/>
        <property name='download.size' value='78964'/>
        <property name='download.md5' value='80672d0f8f508a0dba0919f53dae2972'/>
      </properties>
    </artifact>
    <artifact classifier='osgi.bundle' id='org.eclipse.ui.ide' version='3.8.1.v20120829-085332'>
      <properties size='3'>
        <property name='artifact.size' value='2360552'/>
        <property name='download.size' value='2360552'/>
        <property name='download.md5' value='9eade4e901f0258658cd167a18552ad7'/>
      </properties>
    </artifact>
    <artifact classifier='osgi.bundle' id='org.eclipse.equinox.security' version='1.1.100.v20120522-1841'>
      <properties size='3'>
        <property name='artifact.size' value='107460'/>
        <property name='download.size' value='107460'/>
        <property name='download.md5' value='1bcd1fabdc3984788d102ca5b9095243'/>
      </properties>
    </artifact>
    <artifact classifier='binary' id='org.eclipse.equinox.executable_root.gtk.linux.s390x' version='3.6.0.v20120522-1813-7P7OG2BFLWUl7UmbVUO9iCm'>
      <properties size='1'>
        <property name='download.size' value='40373'/>
      </properties>
    </artifact>
    <artifact classifier='binary' id='org.eclipse.equinox.executable_root.win32.win32.ia64' version='3.6.0.v20120522-1813-7P7OG2BFLWUl7UmbVUO9iCm'>
      <properties size='1'>
        <property name='download.size' value='217339'/>
      </properties>
    </artifact>
    <artifact classifier='osgi.bundle' id='com.jcraft.jsch' version='0.1.46.v201205102330'>
      <properties size='3'>
        <property name='artifact.size' value='241154'/>
        <property name='download.size' value='241154'/>
        <property name='download.md5' value='313a1e7970f33800711ee5d2bf45e4be'/>
      </properties>
    </artifact>
    <artifact classifier='osgi.bundle' id='org.apache.commons.codec' version='1.3.0.v201101211617'>
      <properties size='3'>
        <property name='artifact.size' value='55011'/>
        <property name='download.size' value='55011'/>
        <property name='download.md5' value='e411b9d204b1a91d62b830a86e1f44ff'/>
      </properties>
    </artifact>
    <artifact classifier='osgi.bundle' id='org.apache.lucene.core' version='2.9.1.v201101211721'>
      <properties size='3'>
        <property name='artifact.size' value='1168475'/>
        <property name='download.size' value='1168475'/>
        <property name='download.md5' value='e9261f1d37045a96e2ede8565e08dc09'/>
      </properties>
    </artifact>
    <artifact classifier='osgi.bundle' id='org.eclipse.ecf.provider.filetransfer' version='3.2.0.v20120610-1946'>
      <properties size='3'>
        <property name='artifact.size' value='127603'/>
        <property name='download.size' value='127603'/>
        <property name='download.md5' value='5b7502d0a94a840e0b781a642952afee'/>
      </properties>
    </artifact>
    <artifact classifier='osgi.bundle' id='org.eclipse.ui.presentations.r21' version='3.2.201.v20120523-1956'>
      <properties size='3'>
        <property name='artifact.size' value='100564'/>
        <property name='download.size' value='100564'/>
        <property name='download.md5' value='56c0e00cccb053df04634ef2c7383cee'/>
      </properties>
    </artifact>
    <artifact classifier='osgi.bundle' id='org.eclipse.update.core.linux' version='3.2.300.v20120530-120908'>
      <properties size='3'>
        <property name='artifact.size' value='9562'/>
        <property name='download.size' value='9562'/>
        <property name='download.md5' value='a859baf6614d785f7403893dff145ebc'/>
      </properties>
    </artifact>
    <artifact classifier='osgi.bundle' id='org.eclipse.ui.workbench.compatibility' version='3.2.101.v20120523-1956'>
      <properties size='2'>
        <property name='artifact.size' value='4096'/>
        <property name='download.size' value='16321'/>
      </properties>
    </artifact>
    <artifact classifier='osgi.bundle' id='org.eclipse.equinox.launcher.win32.win32.x86' version='1.1.200.v20120522-1813'>
      <properties size='2'>
        <property name='artifact.size' value='4096'/>
        <property name='download.size' value='27402'/>
      </properties>
    </artifact>
    <artifact classifier='osgi.bundle' id='org.eclipse.ui.console' version='3.5.100.v20120521-2012'>
      <properties size='3'>
        <property name='artifact.size' value='161181'/>
        <property name='download.size' value='161181'/>
        <property name='download.md5' value='c9846ec10d2b7390d6b4ee20fecc09b4'/>
      </properties>
    </artifact>
    <artifact classifier='osgi.bundle' id='org.eclipse.core.filesystem.win32.x86' version='1.1.300.v20120522-1137'>
      <properties size='3'>
        <property name='artifact.size' value='31292'/>
        <property name='download.size' value='31292'/>
        <property name='download.md5' value='b7a053f7c004d6f558f260a2dc82daac'/>
      </properties>
    </artifact>
    <artifact classifier='osgi.bundle' id='org.eclipse.ui.intro' version='3.4.200.v20120521-2344'>
      <properties size='3'>
        <property name='artifact.size' value='309397'/>
        <property name='download.size' value='309397'/>
        <property name='download.md5' value='7d7c8a8d59370ce8a99256cf49737bbe'/>
      </properties>
    </artifact>
    <artifact classifier='binary' id='org.eclipse.equinox.executable_root.motif.aix.ppc' version='3.6.0.v20120522-1813-7P7OG2BFLWUl7UmbVUO9iCm'>
      <properties size='1'>
        <property name='download.size' value='31558'/>
      </properties>
    </artifact>
    <artifact classifier='osgi.bundle' id='org.eclipse.equinox.jsp.jasper' version='1.0.400.v20120522-2049'>
      <properties size='3'>
        <property name='artifact.size' value='28280'/>
        <property name='download.size' value='28280'/>
        <property name='download.md5' value='13812198e24976b06ca0960286e4aaa8'/>
      </properties>
    </artifact>
    <artifact classifier='osgi.bundle' id='org.apache.felix.gogo.runtime' version='0.8.0.v201108120515'>
      <properties size='3'>
        <property name='artifact.size' value='80002'/>
        <property name='download.size' value='80002'/>
        <property name='download.md5' value='2e37fb079caad9ad8a6512831f95f4af'/>
      </properties>
    </artifact>
    <artifact classifier='binary' id='org.eclipse.equinox.executable_root.motif.linux.x86' version='3.6.0.v20120522-1813-7P7OG2BFLWUl7UmbVUO9iCm'>
      <properties size='1'>
        <property name='download.size' value='889071'/>
      </properties>
    </artifact>
    <artifact classifier='osgi.bundle' id='org.eclipse.equinox.launcher' version='1.3.0.v20120522-1813'>
      <properties size='3'>
        <property name='artifact.size' value='49283'/>
        <property name='download.size' value='49283'/>
        <property name='download.md5' value='3a2ed1425961da0a702f3ad3a58ee4be'/>
      </properties>
    </artifact>
    <artifact classifier='osgi.bundle' id='org.eclipse.core.databinding.beans' version='1.2.200.v20120523-1956'>
      <properties size='3'>
        <property name='artifact.size' value='76646'/>
        <property name='download.size' value='76646'/>
        <property name='download.md5' value='aabaec85dd247896894904121ff7481d'/>
      </properties>
    </artifact>
    <artifact classifier='org.eclipse.update.feature' id='org.eclipse.platform' version='3.8.1.v20120815-074604-9gF7jI7wG5qDyZMWGg8NPvDbfWFWlIJU-kYaOQ'>
      <properties size='3'>
        <property name='artifact.size' value='4096'/>
        <property name='download.size' value='32167'/>
        <property name='download.contentType' value='application/zip'/>
      </properties>
    </artifact>
    <artifact classifier='osgi.bundle' id='org.eclipse.equinox.jsp.jasper.registry' version='1.0.300.v20120522-2049'>
      <properties size='3'>
        <property name='artifact.size' value='12354'/>
        <property name='download.size' value='12354'/>
        <property name='download.md5' value='2f8a4e21911aab702b2751f3eb6ed605'/>
      </properties>
    </artifact>
    <artifact classifier='osgi.bundle' id='org.eclipse.equinox.p2.touchpoint.eclipse' version='2.1.100.v20120428-0117'>
      <properties size='3'>
        <property name='artifact.size' value='125384'/>
        <property name='download.size' value='125384'/>
        <property name='download.md5' value='472cec2718169d5ec0a870a39cbdbccb'/>
      </properties>
    </artifact>
    <artifact classifier='osgi.bundle' id='org.eclipse.equinox.p2.jarprocessor' version='1.0.200.v20110808-1657'>
      <properties size='3'>
        <property name='artifact.size' value='69403'/>
        <property name='download.size' value='69403'/>
        <property name='download.md5' value='b9c739d4ac68571e26f5b641c6ef3b19'/>
      </properties>
    </artifact>
    <artifact classifier='org.eclipse.update.feature' id='org.eclipse.rcp' version='3.8.1.v20120814-105048-92BmGJlFw3Ez0WZ9TxCqgcSVAE'>
      <properties size='3'>
        <property name='artifact.size' value='4096'/>
        <property name='download.size' value='31703'/>
        <property name='download.contentType' value='application/zip'/>
      </properties>
    </artifact>
    <artifact classifier='osgi.bundle' id='org.eclipse.equinox.frameworkadmin.equinox' version='1.0.400.v20120428-0117'>
      <properties size='3'>
        <property name='artifact.size' value='62579'/>
        <property name='download.size' value='62579'/>
        <property name='download.md5' value='df5962535a0cb777cccc71e3f9af47f3'/>
      </properties>
    </artifact>
    <artifact classifier='osgi.bundle' id='org.eclipse.help' version='3.6.0.v20120521-2344'>
      <properties size='3'>
        <property name='artifact.size' value='258844'/>
        <property name='download.size' value='258844'/>
        <property name='download.md5' value='61087037e93ee83fb03e101774bfbf70'/>
      </properties>
    </artifact>
    <artifact classifier='osgi.bundle' id='org.eclipse.core.expressions' version='3.4.400.v20120523-2004'>
      <properties size='3'>
        <property name='artifact.size' value='88229'/>
        <property name='download.size' value='88229'/>
        <property name='download.md5' value='beacb4cbac46b8872a09e43a215ee837'/>
      </properties>
    </artifact>
    <artifact classifier='binary' id='tracker_desktop.product_root.win32.win32.x86' version='0.7.0.201211081713'>
      <properties size='1'>
        <property name='download.size' value='112516'/>
      </properties>
    </artifact>
    <artifact classifier='osgi.bundle' id='org.eclipse.jface.databinding' version='1.6.0.v20120521-2332'>
      <properties size='3'>
        <property name='artifact.size' value='278372'/>
        <property name='download.size' value='278372'/>
        <property name='download.md5' value='afb71fc52a71dad5ba301e3dd0a97911'/>
      </properties>
    </artifact>
    <artifact classifier='osgi.bundle' id='org.eclipse.equinox.util' version='1.0.400.v20120522-2049'>
      <properties size='3'>
        <property name='artifact.size' value='78023'/>
        <property name='download.size' value='78023'/>
        <property name='download.md5' value='311a1f171b9bb532b675b2150387a669'/>
      </properties>
    </artifact>
    <artifact classifier='org.eclipse.update.feature' id='com.verticon.tracker.product.desktop.doc' version='0.1.0.201211081713-13377357553J5H59'>
      <properties size='2'>
        <property name='download.contentType' value='application/zip'/>
        <property name='download.size' value='3811'/>
      </properties>
    </artifact>
    <artifact classifier='osgi.bundle' id='org.eclipse.equinox.p2.ui.sdk' version='1.0.200.v20120515-1650'>
      <properties size='3'>
        <property name='artifact.size' value='42689'/>
        <property name='download.size' value='42689'/>
        <property name='download.md5' value='f90c12ef0992d5b011ef58892fc43144'/>
      </properties>
    </artifact>
    <artifact classifier='binary' id='org.eclipse.equinox.executable_root.cocoa.macosx.x86' version='3.6.0.v20120522-1813-7P7OG2BFLWUl7UmbVUO9iCm'>
      <properties size='1'>
        <property name='download.size' value='17117'/>
      </properties>
    </artifact>
    <artifact classifier='osgi.bundle' id='org.eclipse.core.externaltools' version='1.0.100.v20120521-2012'>
      <properties size='3'>
        <property name='artifact.size' value='41085'/>
        <property name='download.size' value='41085'/>
        <property name='download.md5' value='a88b31fa0d685bf6df6cded0f23e593f'/>
      </properties>
    </artifact>
    <artifact classifier='osgi.bundle' id='org.eclipse.equinox.p2.publisher.eclipse' version='1.1.0.v20120511-1931'>
      <properties size='3'>
        <property name='artifact.size' value='215190'/>
        <property name='download.size' value='215190'/>
        <property name='download.md5' value='0fe6f522e694b0359d2268b422ceac9d'/>
      </properties>
    </artifact>
    <artifact classifier='osgi.bundle' id='org.eclipse.equinox.p2.transport.ecf' version='1.0.100.v20120305-0333'>
      <properties size='3'>
        <property name='artifact.size' value='42017'/>
        <property name='download.size' value='42017'/>
        <property name='download.md5' value='4d4924bbd88d6c0977d17b9d746be46f'/>
      </properties>
    </artifact>
    <artifact classifier='osgi.bundle' id='javax.servlet.jsp' version='2.2.0.v201112011158'>
      <properties size='3'>
        <property name='artifact.size' value='107235'/>
        <property name='download.size' value='107235'/>
        <property name='download.md5' value='1b87012bfa0cdd1a29f6ced8325fb94c'/>
      </properties>
    </artifact>
    <artifact classifier='osgi.bundle' id='org.eclipse.equinox.p2.publisher' version='1.2.0.v20120428-0117'>
      <properties size='3'>
        <property name='artifact.size' value='105935'/>
        <property name='download.size' value='105935'/>
        <property name='download.md5' value='56c1514eef86f733f76839b5612215c0'/>
      </properties>
    </artifact>
    <artifact classifier='osgi.bundle' id='org.eclipse.text' version='3.5.200.v20120523-1310'>
      <properties size='3'>
        <property name='artifact.size' value='249360'/>
        <property name='download.size' value='249360'/>
        <property name='download.md5' value='ddb7fbd4f0f30e7c60054aac99c88d52'/>
      </properties>
    </artifact>
    <artifact classifier='binary' id='org.eclipse.equinox.executable_root.win32.win32.x86' version='3.6.0.v20120522-1813-7P7OG2BFLWUl7UmbVUO9iCm'>
      <properties size='1'>
        <property name='download.size' value='114272'/>
      </properties>
    </artifact>
    <artifact classifier='osgi.bundle' id='org.eclipse.ui.ide.application' version='1.0.400.v20120523-1956'>
      <properties size='3'>
        <property name='artifact.size' value='66382'/>
        <property name='download.size' value='66382'/>
        <property name='download.md5' value='a1a121e12b21aaad36579100f9ac1279'/>
      </properties>
    </artifact>
    <artifact classifier='osgi.bundle' id='org.eclipse.search' version='3.8.0.v20120523-1540'>
      <properties size='3'>
        <property name='artifact.size' value='470070'/>
        <property name='download.size' value='470070'/>
        <property name='download.md5' value='479aeebdac4d134a00e4656f22cabec9'/>
      </properties>
    </artifact>
    <artifact classifier='osgi.bundle' id='org.eclipse.core.runtime.compatibility.auth' version='3.2.300.v20120523-2004'>
      <properties size='3'>
        <property name='artifact.size' value='21532'/>
        <property name='download.size' value='21532'/>
        <property name='download.md5' value='7d997f76cf345f36f99ce445001b5bd9'/>
      </properties>
    </artifact>
    <artifact classifier='osgi.bundle' id='org.eclipse.equinox.p2.garbagecollector' version='1.0.200.v20110808-1657'>
      <properties size='3'>
        <property name='artifact.size' value='26235'/>
        <property name='download.size' value='26235'/>
        <property name='download.md5' value='37d25158764f4823904c00afcf00fd8e'/>
      </properties>
    </artifact>
    <artifact classifier='osgi.bundle' id='org.eclipse.equinox.http.servlet' version='1.1.300.v20120522-1841'>
      <properties size='3'>
        <property name='artifact.size' value='45070'/>
        <property name='download.size' value='45070'/>
        <property name='download.md5' value='cad1357ab25a9e5150d3aa8056c9137c'/>
      </properties>
    </artifact>
    <artifact classifier='osgi.bundle' id='org.eclipse.core.runtime.compatibility' version='3.2.200.v20120521-2346'>
      <properties size='3'>
        <property name='artifact.size' value='94012'/>
        <property name='download.size' value='94012'/>
        <property name='download.md5' value='3d39c59ef5ae20ef1ee8f774c0f23e25'/>
      </properties>
    </artifact>
    <artifact classifier='osgi.bundle' id='org.eclipse.equinox.simpleconfigurator' version='1.0.301.v20120828-033635'>
      <properties size='3'>
        <property name='artifact.size' value='40704'/>
        <property name='download.size' value='40704'/>
        <property name='download.md5' value='81096359ecd05496a64489e2cd916b58'/>
      </properties>
    </artifact>
    <artifact classifier='org.eclipse.update.feature' id='com.verticon.tracker.base.dep' version='0.5.0.201211081713-7C3FR8DcTGOTHkZTHQZgm'>
      <properties size='2'>
        <property name='download.contentType' value='application/zip'/>
        <property name='download.size' value='4025'/>
      </properties>
    </artifact>
    <artifact classifier='osgi.bundle' id='org.osgilab.bundles.monitoradmin' version='1.0.1'>
      <properties size='3'>
        <property name='artifact.size' value='23022'/>
        <property name='download.size' value='23022'/>
        <property name='download.md5' value='337238d9899a4c483b511698b8d74d19'/>
      </properties>
    </artifact>
    <artifact classifier='binary' id='org.eclipse.equinox.executable_root.gtk.aix.ppc64' version='3.6.0.v20120522-1813-7P7OG2BFLWUl7UmbVUO9iCm'>
      <properties size='1'>
        <property name='download.size' value='242157'/>
      </properties>
    </artifact>
    <artifact classifier='osgi.bundle' id='org.eclipse.ecf.ssl' version='1.0.100.v20120610-1946'>
      <properties size='3'>
        <property name='artifact.size' value='12773'/>
        <property name='download.size' value='12773'/>
        <property name='download.md5' value='b052ff6a8a4db2db915f9eac690e034e'/>
      </properties>
    </artifact>
    <artifact classifier='osgi.bundle' id='org.eclipse.core.variables' version='3.2.600.v20120521-2012'>
      <properties size='3'>
        <property name='artifact.size' value='34352'/>
        <property name='download.size' value='34352'/>
        <property name='download.md5' value='fbaddbd81e17937f307f8753fc2a712c'/>
      </properties>
    </artifact>
    <artifact classifier='osgi.bundle' id='org.eclipse.ecf.provider.filetransfer.ssl' version='1.0.0.v20120610-1946'>
      <properties size='3'>
        <property name='artifact.size' value='9672'/>
        <property name='download.size' value='9672'/>
        <property name='download.md5' value='e5df22a184e7f327dc820e2ff85578f3'/>
      </properties>
    </artifact>
    <artifact classifier='osgi.bundle' id='org.eclipse.equinox.console' version='1.0.0.v20120522-1841'>
      <properties size='3'>
        <property name='artifact.size' value='111184'/>
        <property name='download.size' value='111184'/>
        <property name='download.md5' value='ca2af277d9245744e60e1382b242f4e1'/>
      </properties>
    </artifact>
    <artifact classifier='osgi.bundle' id='org.eclipse.equinox.launcher.gtk.linux.x86' version='1.1.200.v20120522-1813'>
      <properties size='2'>
        <property name='artifact.size' value='4096'/>
        <property name='download.size' value='75238'/>
      </properties>
    </artifact>
    <artifact classifier='osgi.bundle' id='org.eclipse.ecf' version='3.1.300.v20120610-1946'>
      <properties size='3'>
        <property name='artifact.size' value='94181'/>
        <property name='download.size' value='94181'/>
        <property name='download.md5' value='609ccf02b53ced13b8682bffb8d7bc61'/>
      </properties>
    </artifact>
    <artifact classifier='osgi.bundle' id='org.eclipse.jetty.continuation' version='8.1.3.v20120522'>
      <properties size='3'>
        <property name='artifact.size' value='27328'/>
        <property name='download.size' value='27328'/>
        <property name='download.md5' value='b5bc37636b44fd1a69759b25bf60c2ce'/>
      </properties>
    </artifact>
    <artifact classifier='osgi.bundle' id='org.eclipse.equinox.p2.ui' version='2.2.0.v20120524-0542'>
      <properties size='3'>
        <property name='artifact.size' value='521138'/>
        <property name='download.size' value='521138'/>
        <property name='download.md5' value='ba866e44d14dbc5c259f1de72525f6d5'/>
      </properties>
    </artifact>
    <artifact classifier='osgi.bundle' id='org.apache.felix.gogo.shell' version='0.8.0.v201110170705'>
      <properties size='3'>
        <property name='artifact.size' value='60824'/>
        <property name='download.size' value='60824'/>
        <property name='download.md5' value='b852cd5c878c9f9b963892e5d13f032c'/>
      </properties>
    </artifact>
    <artifact classifier='osgi.bundle' id='org.apache.lucene.analysis' version='2.9.1.v201101211721'>
      <properties size='3'>
        <property name='artifact.size' value='216089'/>
        <property name='download.size' value='216089'/>
        <property name='download.md5' value='e2878a16d87126f4074780f27a29aceb'/>
      </properties>
    </artifact>
    <artifact classifier='binary' id='org.eclipse.equinox.executable_root.motif.solaris.sparc' version='3.6.0.v20120522-1813-7P7OG2BFLWUl7UmbVUO9iCm'>
      <properties size='1'>
        <property name='download.size' value='24597'/>
      </properties>
    </artifact>
    <artifact classifier='osgi.bundle' id='org.eclipse.help.base' version='3.6.100.v201209141540'>
      <properties size='3'>
        <property name='artifact.size' value='421177'/>
        <property name='download.size' value='421177'/>
        <property name='download.md5' value='45e903211f95d671efe076ed6d1a0ff5'/>
      </properties>
    </artifact>
    <artifact classifier='binary' id='org.eclipse.equinox.executable_root.carbon.macosx.ppc' version='3.6.0.v20120522-1813-7P7OG2BFLWUl7UmbVUO9iCm'>
      <properties size='1'>
        <property name='download.size' value='18001'/>
      </properties>
    </artifact>
    <artifact classifier='osgi.bundle' id='org.eclipse.update.ui' version='3.3.0.v20120523-1742'>
      <properties size='3'>
        <property name='artifact.size' value='508620'/>
        <property name='download.size' value='508620'/>
        <property name='download.md5' value='be0e124453a5dc51f15813cd618f5e3c'/>
      </properties>
    </artifact>
    <artifact classifier='osgi.bundle' id='org.eclipse.equinox.security.win32.x86' version='1.0.300.v20120522-2049'>
      <properties size='3'>
        <property name='artifact.size' value='23213'/>
        <property name='download.size' value='23213'/>
        <property name='download.md5' value='f2cfb9ab4c02ed7fad08e0a05a1c3041'/>
      </properties>
    </artifact>
    <artifact classifier='osgi.bundle' id='org.eclipse.jetty.http' version='8.1.3.v20120522'>
      <properties size='3'>
        <property name='artifact.size' value='101528'/>
        <property name='download.size' value='101528'/>
        <property name='download.md5' value='11f4315e13559222b8458e770752b5d6'/>
      </properties>
    </artifact>
    <artifact classifier='osgi.bundle' id='com.verticon.osgi.monitor' version='1.0.0.201211081713'>
      <properties size='2'>
        <property name='artifact.size' value='4096'/>
        <property name='download.size' value='8313'/>
      </properties>
    </artifact>
    <artifact classifier='osgi.bundle' id='org.eclipse.equinox.http.registry' version='1.1.200.v20120522-2049'>
      <properties size='3'>
        <property name='artifact.size' value='45222'/>
        <property name='download.size' value='45222'/>
        <property name='download.md5' value='0f8af82f092b196c5457ef8239b59719'/>
      </properties>
    </artifact>
    <artifact classifier='osgi.bundle' id='org.eclipse.ui.views.properties.tabbed' version='3.5.300.v20120523-1956'>
      <properties size='3'>
        <property name='artifact.size' value='105404'/>
        <property name='download.size' value='105404'/>
        <property name='download.md5' value='2890aa45f41a945dde71b83d8f6323db'/>
      </properties>
    </artifact>
    <artifact classifier='osgi.bundle' id='org.eclipse.ltk.core.refactoring' version='3.6.0.v20120523-1543'>
      <properties size='3'>
        <property name='artifact.size' value='325762'/>
        <property name='download.size' value='325762'/>
        <property name='download.md5' value='8068123d55519cbb5b14a3403e67f743'/>
      </properties>
    </artifact>
    <artifact classifier='osgi.bundle' id='org.eclipse.ecf.provider.filetransfer.httpclient.ssl' version='1.0.0.v20120610-1946'>
      <properties size='3'>
        <property name='artifact.size' value='17935'/>
        <property name='download.size' value='17935'/>
        <property name='download.md5' value='a02fe0b62a3a83dbcfaad5017c7efa68'/>
      </properties>
    </artifact>
    <artifact classifier='binary' id='org.eclipse.equinox.executable_root.gtk.linux.ppc64' version='3.6.0.v20120522-1813-7P7OG2BFLWUl7UmbVUO9iCm'>
      <properties size='1'>
        <property name='download.size' value='39407'/>
      </properties>
    </artifact>
    <artifact classifier='osgi.bundle' id='org.eclipse.ecf.provider.filetransfer.httpclient' version='4.0.200.v20120610-1946'>
      <properties size='3'>
        <property name='artifact.size' value='74130'/>
        <property name='download.size' value='74130'/>
        <property name='download.md5' value='73d96667128a32d5b201c54a55e30c1d'/>
      </properties>
    </artifact>
    <artifact classifier='osgi.bundle' id='org.eclipse.equinox.p2.ql' version='2.0.100.v20110808-1657'>
      <properties size='3'>
        <property name='artifact.size' value='9258'/>
        <property name='download.size' value='9258'/>
        <property name='download.md5' value='94ec0de4cddffb9b321136e5bf8423e9'/>
      </properties>
    </artifact>
    <artifact classifier='osgi.bundle' id='org.eclipse.equinox.ds' version='1.4.0.v20120522-1841'>
      <properties size='3'>
        <property name='artifact.size' value='194030'/>
        <property name='download.size' value='194030'/>
        <property name='download.md5' value='3ae7b28413cd732ec295202f153489c8'/>
      </properties>
    </artifact>
    <artifact classifier='osgi.bundle' id='org.eclipse.equinox.p2.extensionlocation' version='1.2.100.v20110808-1657'>
      <properties size='3'>
        <property name='artifact.size' value='35834'/>
        <property name='download.size' value='35834'/>
        <property name='download.md5' value='449c4dca1b04db5aaf5723af1cf0e85a'/>
      </properties>
    </artifact>
    <artifact classifier='osgi.bundle' id='org.apache.commons.logging' version='1.0.4.v201101211617'>
      <properties size='3'>
        <property name='artifact.size' value='45405'/>
        <property name='download.size' value='45405'/>
        <property name='download.md5' value='d5063f3bb64c7039056f6269a3f9ecc2'/>
      </properties>
    </artifact>
    <artifact classifier='osgi.bundle' id='org.apache.jasper.glassfish' version='2.2.2.v201205150955'>
      <properties size='3'>
        <property name='artifact.size' value='2383691'/>
        <property name='download.size' value='2383691'/>
        <property name='download.md5' value='4acf0e6fa89396eaa5bf05a7bc42e0dd'/>
      </properties>
    </artifact>
    <artifact classifier='binary' id='tracker_desktop.product_root.gtk.linux.x86' version='0.7.0.201211081713'>
      <properties size='1'>
        <property name='download.size' value='171566'/>
      </properties>
    </artifact>
    <artifact classifier='osgi.bundle' id='org.eclipse.equinox.bidi' version='0.9.0.v20120522-1841'>
      <properties size='3'>
        <property name='artifact.size' value='49551'/>
        <property name='download.size' value='49551'/>
        <property name='download.md5' value='49b3b8782be5ebf79ea798a735ec2f72'/>
      </properties>
    </artifact>
    <artifact classifier='osgi.bundle' id='org.eclipse.core.filesystem' version='1.3.200.v20120522-2012'>
      <properties size='3'>
        <property name='artifact.size' value='57914'/>
        <property name='download.size' value='57914'/>
        <property name='download.md5' value='7c4dfea26959218f2af36efb7934d68f'/>
      </properties>
    </artifact>
    <artifact classifier='osgi.bundle' id='org.eclipse.equinox.p2.ui.importexport' version='1.0.1.v20110818-1344'>
      <properties size='3'>
        <property name='artifact.size' value='117500'/>
        <property name='download.size' value='117500'/>
        <property name='download.md5' value='0545c7b0a07ee99e8826df617e4feee8'/>
      </properties>
    </artifact>
    <artifact classifier='osgi.bundle' id='org.eclipse.team.ui' version='3.6.200.v20120522-1148'>
      <properties size='3'>
        <property name='artifact.size' value='1444122'/>
        <property name='download.size' value='1444122'/>
        <property name='download.md5' value='0ef617bfb0ba79c33db873e83296fe2e'/>
      </properties>
    </artifact>
    <artifact classifier='osgi.bundle' id='org.eclipse.jetty.security' version='8.1.3.v20120522'>
      <properties size='3'>
        <property name='artifact.size' value='95308'/>
        <property name='download.size' value='95308'/>
        <property name='download.md5' value='ff68ed7a0717e71c46ceedd03166a2d1'/>
      </properties>
    </artifact>
    <artifact classifier='osgi.bundle' id='org.eclipse.equinox.p2.directorywatcher' version='1.0.300.v20110808-1657'>
      <properties size='3'>
        <property name='artifact.size' value='33782'/>
        <property name='download.size' value='33782'/>
        <property name='download.md5' value='1b4753a58046577282c250c0c307bbfa'/>
      </properties>
    </artifact>
    <artifact classifier='osgi.bundle' id='org.eclipse.jetty.io' version='8.1.3.v20120522'>
      <properties size='3'>
        <property name='artifact.size' value='111094'/>
        <property name='download.size' value='111094'/>
        <property name='download.md5' value='4872b3a2807c3b90dfe600b74519adf4'/>
      </properties>
    </artifact>
    <artifact classifier='osgi.bundle' id='com.verticon.tracker.product.desktop.doc' version='0.1.4.201211081713'>
      <properties size='2'>
        <property name='artifact.size' value='4096'/>
        <property name='download.size' value='448364'/>
      </properties>
    </artifact>
    <artifact classifier='osgi.bundle' id='org.eclipse.ui' version='3.8.0.v20120523-1546'>
      <properties size='3'>
        <property name='artifact.size' value='154480'/>
        <property name='download.size' value='154480'/>
        <property name='download.md5' value='9da6bd0182d356c8afc29f0bd9fbd378'/>
      </properties>
    </artifact>
    <artifact classifier='osgi.bundle' id='org.eclipse.core.databinding' version='1.4.1.v20120521-2332'>
      <properties size='3'>
        <property name='artifact.size' value='202252'/>
        <property name='download.size' value='202252'/>
        <property name='download.md5' value='066715d5df473f4d42fbff7f33e0ce39'/>
      </properties>
    </artifact>
    <artifact classifier='osgi.bundle' id='org.eclipse.equinox.event' version='1.2.200.v20120522-2049'>
      <properties size='3'>
        <property name='artifact.size' value='33748'/>
        <property name='download.size' value='33748'/>
        <property name='download.md5' value='c54c7c41df432e0cb11f9c49131a6f58'/>
      </properties>
    </artifact>
    <artifact classifier='osgi.bundle' id='org.eclipse.compare' version='3.5.300.v20120522-1148'>
      <properties size='3'>
        <property name='artifact.size' value='737820'/>
        <property name='download.size' value='737820'/>
        <property name='download.md5' value='845f86491d19b31cbdfa7b24e06d81dd'/>
      </properties>
    </artifact>
    <artifact classifier='osgi.bundle' id='org.eclipse.platform.doc.user' version='3.8.0.v20120829-071851'>
      <properties size='3'>
        <property name='artifact.size' value='7037313'/>
        <property name='download.size' value='7037313'/>
        <property name='download.md5' value='60083b5c03f53630e23298565e67982b'/>
      </properties>
    </artifact>
    <artifact classifier='osgi.bundle' id='org.eclipse.jsch.core' version='1.1.400.v20120522-1148'>
      <properties size='3'>
        <property name='artifact.size' value='37558'/>
        <property name='download.size' value='37558'/>
        <property name='download.md5' value='ba17de9fcccddc009d9f9d6aa20dba3c'/>
      </properties>
    </artifact>
    <artifact classifier='osgi.bundle' id='com.verticon.tracker.doc' version='0.3.0.201211081713'>
      <properties size='2'>
        <property name='artifact.size' value='4096'/>
        <property name='download.size' value='215741'/>
      </properties>
    </artifact>
    <artifact classifier='osgi.bundle' id='com.sun.el' version='2.2.0.v201108011116'>
      <properties size='3'>
        <property name='artifact.size' value='130602'/>
        <property name='download.size' value='130602'/>
        <property name='download.md5' value='26ae690e40e51c508b4531ceb016a4e4'/>
      </properties>
    </artifact>
    <artifact classifier='osgi.bundle' id='org.eclipse.update.core' version='3.2.600.v20120530-120908'>
      <properties size='3'>
        <property name='artifact.size' value='596942'/>
        <property name='download.size' value='596942'/>
        <property name='download.md5' value='aa72ca85f95a77cfa218d8ed7f52bac1'/>
      </properties>
    </artifact>
    <artifact classifier='osgi.bundle' id='org.eclipse.ui.workbench.texteditor' version='3.8.0.v20120523-1310'>
      <properties size='3'>
        <property name='artifact.size' value='584029'/>
        <property name='download.size' value='584029'/>
        <property name='download.md5' value='c2738bac42c20205909c2ee0fe11d1bf'/>
      </properties>
    </artifact>
    <artifact classifier='org.eclipse.update.feature' id='org.eclipse.equinox.p2.core.feature' version='1.1.0.v20120524-0542-8297FncFWmE7h4Asx2cpqz-T38'>
      <properties size='3'>
        <property name='artifact.size' value='4096'/>
        <property name='download.size' value='31406'/>
        <property name='download.contentType' value='application/zip'/>
      </properties>
    </artifact>
    <artifact classifier='org.eclipse.update.feature' id='org.eclipse.equinox.p2.user.ui' version='2.2.0.v20120524-0542-62DG9JXTlSiz-UbcP0w0KGl9CKNP'>
      <properties size='3'>
        <property name='artifact.size' value='4096'/>
        <property name='download.size' value='30989'/>
        <property name='download.contentType' value='application/zip'/>
      </properties>
    </artifact>
    <artifact classifier='osgi.bundle' id='org.eclipse.equinox.p2.artifact.repository' version='1.1.200.v20120430-1959'>
      <properties size='3'>
        <property name='artifact.size' value='137108'/>
        <property name='download.size' value='137108'/>
        <property name='download.md5' value='bfbc5490ea27207594211b1a23d83501'/>
      </properties>
    </artifact>
    <artifact classifier='osgi.bundle' id='org.eclipse.equinox.p2.metadata' version='2.1.0.v20120430-2001'>
      <properties size='3'>
        <property name='artifact.size' value='340685'/>
        <property name='download.size' value='340685'/>
        <property name='download.md5' value='c8827e9dca2984e39a5916c1d829d0e9'/>
      </properties>
    </artifact>
    <artifact classifier='osgi.bundle' id='org.eclipse.ui.navigator' version='3.5.200.v20120523-1956'>
      <properties size='3'>
        <property name='artifact.size' value='406140'/>
        <property name='download.size' value='406140'/>
        <property name='download.md5' value='f6ffa5ec7ef79f35b4c79c4291952483'/>
      </properties>
    </artifact>
    <artifact classifier='osgi.bundle' id='org.eclipse.help.ui' version='3.5.200.v20120521-2344'>
      <properties size='3'>
        <property name='artifact.size' value='499284'/>
        <property name='download.size' value='499284'/>
        <property name='download.md5' value='ae1216ba04c48d7074560ca554d3bbf4'/>
      </properties>
    </artifact>
    <artifact classifier='osgi.bundle' id='org.eclipse.ltk.ui.refactoring' version='3.7.0.v20120523-1543'>
      <properties size='3'>
        <property name='artifact.size' value='458248'/>
        <property name='download.size' value='458248'/>
        <property name='download.md5' value='664e3cc836fc745781c0e47044a8be63'/>
      </properties>
    </artifact>
    <artifact classifier='osgi.bundle' id='org.eclipse.equinox.common' version='3.6.100.v20120522-1841'>
      <properties size='3'>
        <property name='artifact.size' value='106763'/>
        <property name='download.size' value='106763'/>
        <property name='download.md5' value='69da96d4618d94fc2427ee765b6cabd9'/>
      </properties>
    </artifact>
    <artifact classifier='osgi.bundle' id='org.eclipse.core.runtime' version='3.8.0.v20120521-2346'>
      <properties size='3'>
        <property name='artifact.size' value='75328'/>
        <property name='download.size' value='75328'/>
        <property name='download.md5' value='b174f56ce7606ffc1eea492d7a78b503'/>
      </properties>
    </artifact>
    <artifact classifier='osgi.bundle' id='org.eclipse.core.net.linux.x86' version='1.1.200.v20120522-1148'>
      <properties size='3'>
        <property name='artifact.size' value='38043'/>
        <property name='download.size' value='38043'/>
        <property name='download.md5' value='064c0626938eec885d31c56779848f49'/>
      </properties>
    </artifact>
    <artifact classifier='binary' id='org.eclipse.equinox.executable_root.cocoa.macosx.x86_64' version='3.6.0.v20120522-1813-7P7OG2BFLWUl7UmbVUO9iCm'>
      <properties size='1'>
        <property name='download.size' value='11035'/>
      </properties>
    </artifact>
    <artifact classifier='osgi.bundle' id='org.sat4j.core' version='2.3.0.v20110329'>
      <properties size='3'>
        <property name='artifact.size' value='210701'/>
        <property name='download.size' value='210701'/>
        <property name='download.md5' value='980266c34f81f1741619257927f58102'/>
      </properties>
    </artifact>
    <artifact classifier='binary' id='org.eclipse.equinox.executable_root.gtk.linux.s390' version='3.6.0.v20120522-1813-7P7OG2BFLWUl7UmbVUO9iCm'>
      <properties size='1'>
        <property name='download.size' value='40159'/>
      </properties>
    </artifact>
    <artifact classifier='osgi.bundle' id='org.eclipse.equinox.p2.updatechecker' version='1.1.200.v20110808-1657'>
      <properties size='3'>
        <property name='artifact.size' value='18007'/>
        <property name='download.size' value='18007'/>
        <property name='download.md5' value='125224203edc476e7b0795d0c79e4523'/>
      </properties>
    </artifact>
    <artifact classifier='osgi.bundle' id='org.eclipse.osgi.services' version='3.3.100.v20120522-1822'>
      <properties size='3'>
        <property name='artifact.size' value='83083'/>
        <property name='download.size' value='83083'/>
        <property name='download.md5' value='9a5a09fd0eb4b75a34f6be9d1daf2aab'/>
      </properties>
    </artifact>
    <artifact classifier='osgi.bundle' id='org.eclipse.core.databinding.property' version='1.4.100.v20120523-1956'>
      <properties size='3'>
        <property name='artifact.size' value='169210'/>
        <property name='download.size' value='169210'/>
        <property name='download.md5' value='81155e6511aca099ac676b9cc1ccc5f8'/>
      </properties>
    </artifact>
    <artifact classifier='osgi.bundle' id='com.verticon.tracker.product.desktop' version='0.7.0.201211081713'>
      <properties size='2'>
        <property name='artifact.size' value='4096'/>
        <property name='download.size' value='710983'/>
      </properties>
    </artifact>
    <artifact classifier='osgi.bundle' id='org.eclipse.swt.gtk.linux.x86' version='3.8.1.v3834e'>
      <properties size='3'>
        <property name='artifact.size' value='2380372'/>
        <property name='download.size' value='2380372'/>
        <property name='download.md5' value='de2fd375607ffb397b81ca6b758ee5f1'/>
      </properties>
    </artifact>
    <artifact classifier='osgi.bundle' id='org.eclipse.ui.views' version='3.6.100.v20120521-2332'>
      <properties size='3'>
        <property name='artifact.size' value='91382'/>
        <property name='download.size' value='91382'/>
        <property name='download.md5' value='d73d00c64e348ffdb823a500b7b36bd7'/>
      </properties>
    </artifact>
    <artifact classifier='binary' id='org.eclipse.equinox.executable_root.gtk.linux.x86' version='3.6.0.v20120522-1813-7P7OG2BFLWUl7UmbVUO9iCm'>
      <properties size='1'>
        <property name='download.size' value='161418'/>
      </properties>
    </artifact>
    <artifact classifier='osgi.bundle' id='org.eclipse.equinox.p2.director.app' version='1.0.300.v20120428-0517'>
      <properties size='3'>
        <property name='artifact.size' value='50372'/>
        <property name='download.size' value='50372'/>
        <property name='download.md5' value='3024ad5143c398d3394f2807eb522b62'/>
      </properties>
    </artifact>
    <artifact classifier='osgi.bundle' id='org.eclipse.core.filesystem.linux.x86' version='1.4.0.v20120522-1137'>
      <properties size='3'>
        <property name='artifact.size' value='10489'/>
        <property name='download.size' value='10489'/>
        <property name='download.md5' value='24408c05f7007253ab769b3f7b50f8a1'/>
      </properties>
    </artifact>
    <artifact classifier='osgi.bundle' id='org.eclipse.rcp' version='3.8.0.v201209141540'>
      <properties size='3'>
        <property name='artifact.size' value='13393'/>
        <property name='download.size' value='13393'/>
        <property name='download.md5' value='78ef844232f1c5733147b05d7bfed8a9'/>
      </properties>
    </artifact>
    <artifact classifier='osgi.bundle' id='org.eclipse.equinox.p2.director' version='2.2.0.v20120524-0542'>
      <properties size='3'>
        <property name='artifact.size' value='96471'/>
        <property name='download.size' value='96471'/>
        <property name='download.md5' value='cd2eb2a6d041265ab2ecaa8bfe3dcc4f'/>
      </properties>
    </artifact>
    <artifact classifier='osgi.bundle' id='org.eclipse.core.runtime.compatibility.registry' version='3.5.100.v20120521-2346'>
      <properties size='2'>
        <property name='artifact.size' value='4096'/>
        <property name='download.size' value='19323'/>
      </properties>
    </artifact>
    <artifact classifier='osgi.bundle' id='org.eclipse.core.resources.win32.x86' version='3.5.100.v20120522-1137'>
      <properties size='3'>
        <property name='artifact.size' value='18225'/>
        <property name='download.size' value='18225'/>
        <property name='download.md5' value='93ac011454bff5b84534dba78c27f077'/>
      </properties>
    </artifact>
    <artifact classifier='osgi.bundle' id='org.eclipse.osgi.util' version='3.2.300.v20120522-1822'>
      <properties size='3'>
        <property name='artifact.size' value='24974'/>
        <property name='download.size' value='24974'/>
        <property name='download.md5' value='df9a313bd5cf0fbb0970d822c2faa234'/>
      </properties>
    </artifact>
    <artifact classifier='osgi.bundle' id='org.eclipse.ui.win32' version='3.2.300.v20120523-1956'>
      <properties size='3'>
        <property name='artifact.size' value='25866'/>
        <property name='download.size' value='25866'/>
        <property name='download.md5' value='10c6408a206c7d3f617fa552900f39e0'/>
      </properties>
    </artifact>
    <artifact classifier='osgi.bundle' id='org.eclipse.core.contenttype' version='3.4.200.v20120523-2004'>
      <properties size='3'>
        <property name='artifact.size' value='93177'/>
        <property name='download.size' value='93177'/>
        <property name='download.md5' value='9536ff186ace5fb031198c2ad24219c4'/>
      </properties>
    </artifact>
    <artifact classifier='osgi.bundle' id='org.eclipse.equinox.preferences' version='3.5.0.v20120522-1841'>
      <properties size='3'>
        <property name='artifact.size' value='126763'/>
        <property name='download.size' value='126763'/>
        <property name='download.md5' value='c8c9d43f23d5882763d32c9779777561'/>
      </properties>
    </artifact>
    <artifact classifier='osgi.bundle' id='org.eclipse.equinox.p2.console' version='1.0.300.v20120429-0125'>
      <properties size='3'>
        <property name='artifact.size' value='28275'/>
        <property name='download.size' value='28275'/>
        <property name='download.md5' value='74cea6f774b86bc2c76ba23263a240bb'/>
      </properties>
    </artifact>
    <artifact classifier='osgi.bundle' id='javax.el' version='2.2.0.v201108011116'>
      <properties size='3'>
        <property name='artifact.size' value='52319'/>
        <property name='download.size' value='52319'/>
        <property name='download.md5' value='ff8240a6d97eb014d9440d1dd3ac0312'/>
      </properties>
    </artifact>
    <artifact classifier='org.eclipse.update.feature' id='org.eclipse.equinox.p2.extras.feature' version='1.1.0.v20120524-0542-7A6FEcDiVOTg1Q_HuZrEuBty3dqr'>
      <properties size='3'>
        <property name='artifact.size' value='4096'/>
        <property name='download.size' value='31042'/>
        <property name='download.contentType' value='application/zip'/>
      </properties>
    </artifact>
    <artifact classifier='osgi.bundle' id='org.eclipse.ui.intro.universal' version='3.2.600.v20120521-2344'>
      <properties size='2'>
        <property name='artifact.size' value='4096'/>
        <property name='download.size' value='1637386'/>
      </properties>
    </artifact>
    <artifact classifier='binary' id='tracker_desktop.product.root.feature_root' version='0.7.0.201211081713'>
      <properties size='1'>
        <property name='download.size' value='297'/>
      </properties>
    </artifact>
    <artifact classifier='osgi.bundle' id='org.apache.ant' version='1.8.3.v20120321-1730'>
      <properties size='2'>
        <property name='artifact.size' value='4096'/>
        <property name='download.size' value='2359313'/>
      </properties>
    </artifact>
    <artifact classifier='binary' id='org.eclipse.equinox.executable_root.gtk.linux.ppc' version='3.6.0.v20120522-1813-7P7OG2BFLWUl7UmbVUO9iCm'>
      <properties size='1'>
        <property name='download.size' value='168546'/>
      </properties>
    </artifact>
    <artifact classifier='osgi.bundle' id='org.eclipse.core.resources' version='3.8.1.v20120802-154922'>
      <properties size='3'>
        <property name='artifact.size' value='809714'/>
        <property name='download.size' value='809714'/>
        <property name='download.md5' value='16f77f717b585e959d41d089a742d426'/>
      </properties>
    </artifact>
    <artifact classifier='osgi.bundle' id='org.eclipse.jetty.util' version='8.1.3.v20120522'>
      <properties size='3'>
        <property name='artifact.size' value='282738'/>
        <property name='download.size' value='282738'/>
        <property name='download.md5' value='c6f5d51f24541beb306de269170859ad'/>
      </properties>
    </artifact>
    <artifact classifier='binary' id='org.eclipse.equinox.executable_root.motif.hpux.ia64_32' version='3.6.0.v20120522-1813-7P7OG2BFLWUl7UmbVUO9iCm'>
      <properties size='1'>
        <property name='download.size' value='15071'/>
      </properties>
    </artifact>
    <artifact classifier='osgi.bundle' id='org.eclipse.ui.net' version='1.2.101.v20120801-152207'>
      <properties size='3'>
        <property name='artifact.size' value='48971'/>
        <property name='download.size' value='48971'/>
        <property name='download.md5' value='38534ab4e076bf5e6f77720cb30de356'/>
      </properties>
    </artifact>
    <artifact classifier='osgi.bundle' id='org.eclipse.equinox.frameworkadmin' version='2.0.100.v20120606-175127'>
      <properties size='3'>
        <property name='artifact.size' value='36191'/>
        <property name='download.size' value='36191'/>
        <property name='download.md5' value='732e3f4f980380484ce33da45e996050'/>
      </properties>
    </artifact>
    <artifact classifier='osgi.bundle' id='org.eclipse.equinox.p2.operations' version='2.2.0.v20120524-0542'>
      <properties size='3'>
        <property name='artifact.size' value='59720'/>
        <property name='download.size' value='59720'/>
        <property name='download.md5' value='cc5cc1153f532940be284a692a354279'/>
      </properties>
    </artifact>
    <artifact classifier='osgi.bundle' id='org.eclipse.ui.cheatsheets' version='3.4.200.v20120521-2344'>
      <properties size='3'>
        <property name='artifact.size' value='330210'/>
        <property name='download.size' value='330210'/>
        <property name='download.md5' value='1ec62029175d06fcd5a005d561378ce8'/>
      </properties>
    </artifact>
    <artifact classifier='osgi.bundle' id='org.eclipse.help.webapp' version='3.6.101.v20120717-130216'>
      <properties size='3'>
        <property name='artifact.size' value='609551'/>
        <property name='download.size' value='609551'/>
        <property name='download.md5' value='8b077f690380376b5e9b15f41324ff4f'/>
      </properties>
    </artifact>
    <artifact classifier='osgi.bundle' id='org.eclipse.equinox.security.ui' version='1.1.100.v20120522-2049'>
      <properties size='3'>
        <property name='artifact.size' value='215473'/>
        <property name='download.size' value='215473'/>
        <property name='download.md5' value='82e6b3fd02b7fb59ac319d9cbbb2d942'/>
      </properties>
    </artifact>
    <artifact classifier='osgi.bundle' id='org.eclipse.jetty.servlet' version='8.1.3.v20120522'>
      <properties size='3'>
        <property name='artifact.size' value='102989'/>
        <property name='download.size' value='102989'/>
        <property name='download.md5' value='4b26b3a55a89b65e07827e16819d97a6'/>
      </properties>
    </artifact>
    <artifact classifier='osgi.bundle' id='org.eclipse.help.appserver' version='3.1.400.v20120521-2344'>
      <properties size='3'>
        <property name='artifact.size' value='19532'/>
        <property name='download.size' value='19532'/>
        <property name='download.md5' value='7c7ff5a5b727b67ffc97ceecdfedc284'/>
      </properties>
    </artifact>
    <artifact classifier='osgi.bundle' id='org.eclipse.core.databinding.observable' version='1.4.1.v20120521-2332'>
      <properties size='3'>
        <property name='artifact.size' value='297396'/>
        <property name='download.size' value='297396'/>
        <property name='download.md5' value='304c2129938317ad20059fbb002c875f'/>
      </properties>
    </artifact>
    <artifact classifier='osgi.bundle' id='org.eclipse.ui.externaltools' version='3.2.100.v20120530-1753'>
      <properties size='3'>
        <property name='artifact.size' value='137309'/>
        <property name='download.size' value='137309'/>
        <property name='download.md5' value='ce0e4115bf9f820217f2714967a0860b'/>
      </properties>
    </artifact>
    <artifact classifier='osgi.bundle' id='org.eclipse.core.commands' version='3.6.1.v20120521-2332'>
      <properties size='3'>
        <property name='artifact.size' value='108735'/>
        <property name='download.size' value='108735'/>
        <property name='download.md5' value='09f59350d78167a7be85ab98ab4f9716'/>
      </properties>
    </artifact>
    <artifact classifier='osgi.bundle' id='org.eclipse.equinox.p2.reconciler.dropins' version='1.1.200.v20120301-2145'>
      <properties size='3'>
        <property name='artifact.size' value='48731'/>
        <property name='download.size' value='48731'/>
        <property name='download.md5' value='521f43131f72e620c39175c14b0e6fe2'/>
      </properties>
    </artifact>
    <artifact classifier='binary' id='org.eclipse.equinox.executable_root.gtk.aix.ppc' version='3.6.0.v20120522-1813-7P7OG2BFLWUl7UmbVUO9iCm'>
      <properties size='1'>
        <property name='download.size' value='238222'/>
      </properties>
    </artifact>
    <artifact classifier='osgi.bundle' id='org.eclipse.equinox.p2.metadata.repository' version='1.2.100.v20120524-1717'>
      <properties size='3'>
        <property name='artifact.size' value='118133'/>
        <property name='download.size' value='118133'/>
        <property name='download.md5' value='e54a66b29c76e7bb23a29dd4b40f2c0b'/>
      </properties>
    </artifact>
    <artifact classifier='binary' id='org.eclipse.equinox.executable_root.wpf.win32.x86' version='3.6.0.v20120522-1813-7P7OG2BFLWUl7UmbVUO9iCm'>
      <properties size='1'>
        <property name='download.size' value='137906'/>
      </properties>
    </artifact>
    <artifact classifier='binary' id='org.eclipse.equinox.executable_root.win32.win32.x86_64' version='3.6.0.v20120522-1813-7P7OG2BFLWUl7UmbVUO9iCm'>
      <properties size='1'>
        <property name='download.size' value='116068'/>
      </properties>
    </artifact>
    <artifact classifier='osgi.bundle' id='org.eclipse.jface.text' version='3.8.1.v20120828-155502'>
      <properties size='3'>
        <property name='artifact.size' value='991596'/>
        <property name='download.size' value='991596'/>
        <property name='download.md5' value='3bd42f2eeac135f5c5da4647d1abe698'/>
      </properties>
    </artifact>
    <artifact classifier='org.eclipse.update.feature' id='org.eclipse.help' version='1.4.1.v20120726-050831-8R7xFOUFLWUl7MoSKV_OFXl27'>
      <properties size='3'>
        <property name='artifact.size' value='4096'/>
        <property name='download.size' value='31140'/>
        <property name='download.contentType' value='application/zip'/>
      </properties>
    </artifact>
    <artifact classifier='osgi.bundle' id='org.eclipse.equinox.cm' version='1.0.400.v20120522-1841'>
      <properties size='3'>
        <property name='artifact.size' value='63690'/>
        <property name='download.size' value='63690'/>
        <property name='download.md5' value='aae15a91cc8cd0bedd3645c5c746b5ed'/>
      </properties>
    </artifact>
    <artifact classifier='osgi.bundle' id='org.eclipse.ui.navigator.resources' version='3.4.400.v20120523-1956'>
      <properties size='3'>
        <property name='artifact.size' value='120316'/>
        <property name='download.size' value='120316'/>
        <property name='download.md5' value='671469d2f0e003a4f7a1c4180e8ffff9'/>
      </properties>
    </artifact>
    <artifact classifier='osgi.bundle' id='org.eclipse.update.configurator' version='3.3.200.v20120523-1742'>
      <properties size='3'>
        <property name='artifact.size' value='101129'/>
        <property name='download.size' value='101129'/>
        <property name='download.md5' value='4b9ea74c7e01b23f3e664629d7025082'/>
      </properties>
    </artifact>
    <artifact classifier='osgi.bundle' id='org.eclipse.equinox.registry' version='3.5.200.v20120522-1841'>
      <properties size='3'>
        <property name='artifact.size' value='184238'/>
        <property name='download.size' value='184238'/>
        <property name='download.md5' value='e181eb666dee9208c68bb736f1a03651'/>
      </properties>
    </artifact>
    <artifact classifier='osgi.bundle' id='org.eclipse.equinox.p2.engine' version='2.2.0.v20120501-1502'>
      <properties size='3'>
        <property name='artifact.size' value='197429'/>
        <property name='download.size' value='197429'/>
        <property name='download.md5' value='93a9be0dcc0f5cb46b02783b887c5980'/>
      </properties>
    </artifact>
    <artifact classifier='osgi.bundle' id='org.eclipse.jetty.server' version='8.1.3.v20120522'>
      <properties size='3'>
        <property name='artifact.size' value='344666'/>
        <property name='download.size' value='344666'/>
        <property name='download.md5' value='7884288eef91b5ba4761895fdb299c6a'/>
      </properties>
    </artifact>
    <artifact classifier='binary' id='org.eclipse.equinox.executable_root.gtk.hpux.ia64_32' version='3.6.0.v20120522-1813-7P7OG2BFLWUl7UmbVUO9iCm'>
      <properties size='1'>
        <property name='download.size' value='14173'/>
      </properties>
    </artifact>
  </artifacts>
</repository>
