<?xml version="1.0" encoding="UTF-8"?>
<feature
      id="com.verticon.birt.report.loader"
      label="%featureName"
      version="0.1.2.qualifier"
      provider-name="%providerName"
      plugin="com.verticon.birt.report.loader">

   <description>
      %description
   </description>

   <copyright>
      %copyright
   </copyright>

   <license url="http://www.eclipse.org/legal/epl-v10.html">
      %license
   </license>

   <url>
      <discovery label="%TrackerUpdateSiteName" url="http://tracker.verticon.com/Tracker/updates/"/>
   </url>

   <requires>
      <import feature="org.eclipse.ocl.examples" version="3.2.1.v20120919-0602"/>
   </requires>

   <plugin
         id="com.verticon.birt.report.loader"
         download-size="0"
         install-size="0"
         version="0.0.0"
         unpack="false"/>

   <plugin
         id="com.verticon.birt.report.loader.ui"
         download-size="0"
         install-size="0"
         version="0.0.0"
         unpack="false"/>

</feature>
